{
  "event_type": "course_enrolled",
  "topic": "lms.enrollment.created.v1",
  "producer_service": "enrollment-service",
  "schema_version": 1,
  "ownership_status": "deprecated_in_course_service",
  "purpose": "Compatibility alias retained for legacy topic naming while integration fan-out is handled asynchronously via event-ingestion-service to avoid direct course/assessment coupling.",
  "payload": {
    "tenant_id": "string",
    "correlation_id": "string",
    "course_id": "string",
    "enrollment_id": "string",
    "learner_id": "string",
    "enrolled_by": "string",
    "enrollment_source": "self|manager|admin|integration",
    "due_at": "date-time|null",
    "status": "active",
    "enrolled_at": "date-time"
  },
  "consumers": [
    "event-ingestion-service"
  ],
  "downstream_consumers": [
    "progress-service",
    "notification-service",
    "assessment-service",
    "learning-analytics-service",
    "certificate-service"
  ]
}
